{
  "project_info": {
    "project_number": "363035831725",
    "project_id": "tuto-firebase-ninja",
    "storage_bucket": "tuto-firebase-ninja.appspot.com"
  },
  "client": [
    {
      "client_info": {
        "mobilesdk_app_id": "1:363035831725:android:aad9758b07691dace50524",
        "android_client_info": {
          "package_name": "com.example.tuto_firebase"
        }
      },
      "oauth_client": [
        {
          "client_id": "363035831725-inek6bu9adon78kikimdr8nciv56rmf1.apps.googleusercontent.com",
          "client_type": 3
        }
      ],
      "api_key": [
        {
          "current_key": "AIzaSyDHO9GX5mIMCsKIfXOIxikUS5WXcIapAbA"
        }
      ],
      "services": {
        "appinvite_service": {
          "other_platform_oauth_client": [
            {
              "client_id": "363035831725-inek6bu9adon78kikimdr8nciv56rmf1.apps.googleusercontent.com",
              "client_type": 3
            }
          ]
        }
      }
    }
  ],
  "configuration_version": "1"
}